bracketeering/__init__.py
bracketeering/brackets.py
bracketeering/data/__init__.py
bracketeering/data/us_2022.csv
bracketeering/data/us_2023.csv
bracketeering/domain.py
bracketeering-0.1.0.dist-info/WHEEL
bracketeering-0.1.0.dist-info/METADATA
bracketeering-0.1.0.dist-info/RECORD
